{
  "project_info": {
    "project_number": "683756484905",
    "firebase_url": "https://recyclerviewkt-default-rtdb.firebaseio.com",
    "project_id": "recyclerviewkt",
    "storage_bucket": "recyclerviewkt.appspot.com"
  },
  "client": [
    {
      "client_info": {
        "mobilesdk_app_id": "1:683756484905:android:d57b9a7e783fcb35985f38",
        "android_client_info": {
          "package_name": "com.example.samdollarfront"
        }
      },
      "oauth_client": [],
      "api_key": [
        {
          "current_key": "AIzaSyAjmb0A271n7cMFDkzOy9bQv-Jt79Lg2yE"
        }
      ],
      "services": {
        "appinvite_service": {
          "other_platform_oauth_client": []
        }
      }
    }
  ],
  "configuration_version": "1"
}